glue_plotly/__init__.py
glue_plotly/conftest.py
glue_plotly/export_dialog.py
glue_plotly/jupyter_base_export_tool.py
glue_plotly/logo.png
glue_plotly/logo.svg
glue_plotly/sort_components.py
glue_plotly/sort_components.ui
glue_plotly/utils.py
glue_plotly/volume_options.py
glue_plotly/volume_options.ui
glue_plotly/common/__init__.py
glue_plotly/common/base_3d.py
glue_plotly/common/common.py
glue_plotly/common/dendrogram.py
glue_plotly/common/dotplot.py
glue_plotly/common/histogram.py
glue_plotly/common/image.py
glue_plotly/common/profile.py
glue_plotly/common/scatter2d.py
glue_plotly/common/scatter3d.py
glue_plotly/common/volume.py
glue_plotly/common/tests/__init__.py
glue_plotly/common/tests/test_dendrogram.py
glue_plotly/common/tests/test_histogram.py
glue_plotly/common/tests/test_profile.py
glue_plotly/common/tests/test_scatter2d.py
glue_plotly/common/tests/utils.py
glue_plotly/html_exporters/__init__.py
glue_plotly/html_exporters/base_save_hover.py
glue_plotly/html_exporters/hover_utils.py
glue_plotly/html_exporters/jupyter/__init__.py
glue_plotly/html_exporters/jupyter/histogram.py
glue_plotly/html_exporters/jupyter/image.py
glue_plotly/html_exporters/jupyter/profile.py
glue_plotly/html_exporters/jupyter/save_hover.py
glue_plotly/html_exporters/jupyter/save_hover.vue
glue_plotly/html_exporters/jupyter/scatter2d.py
glue_plotly/html_exporters/jupyter/scatter3d.py
glue_plotly/html_exporters/jupyter/volume.py
glue_plotly/html_exporters/jupyter/tests/__init__.py
glue_plotly/html_exporters/jupyter/tests/test_base.py
glue_plotly/html_exporters/jupyter/tests/test_histogram.py
glue_plotly/html_exporters/jupyter/tests/test_image.py
glue_plotly/html_exporters/jupyter/tests/test_ipyvolume_scatter3d.py
glue_plotly/html_exporters/jupyter/tests/test_ipyvolume_volume.py
glue_plotly/html_exporters/jupyter/tests/test_profile.py
glue_plotly/html_exporters/jupyter/tests/test_scatter2d.py
glue_plotly/html_exporters/jupyter/tests/test_vispy_scatter3d.py
glue_plotly-0.13.1.dist-info/licenses/LICENSE
glue_plotly-0.13.1.dist-info/METADATA
glue_plotly-0.13.1.dist-info/WHEEL
glue_plotly-0.13.1.dist-info/entry_points.txt
glue_plotly-0.13.1.dist-info/top_level.txt
glue_plotly-0.13.1.dist-info/RECORD
