Metadata-Version: 2.4
Name: glue-plotly
Version: 0.13.1
Summary: Experimental plot.ly exporters for glue
Home-page: https://github.com/glue-viz/glue-plotly
Author: Thomas Robitaille and Catherine Zucker
Author-email: glue.viz@gmail.com
License: BSD 3-Clause License
Provides: glue_plotly
Requires-Python: >=3.10
License-File: LICENSE
Requires-Dist: glue-core>=1.13.1
Requires-Dist: plotly!=6.0.*
Provides-Extra: test
Requires-Dist: pytest; extra == "test"
Requires-Dist: pytest-cov; extra == "test"
Requires-Dist: mock; extra == "test"
Provides-Extra: qt
Requires-Dist: glue-qt; extra == "qt"
Requires-Dist: PySide2; python_version == "2" and extra == "qt"
Requires-Dist: PyQt5; python_version >= "3" and extra == "qt"
Provides-Extra: 3d
Requires-Dist: glue-vispy-viewers>=1.2.1; extra == "3d"
Provides-Extra: jupyter
Requires-Dist: anywidget; extra == "jupyter"
Requires-Dist: glue-jupyter; extra == "jupyter"
Requires-Dist: ipyvuetify; extra == "jupyter"
Requires-Dist: ipyfilechooser; extra == "jupyter"
Requires-Dist: ipython-genutils; extra == "jupyter"
Dynamic: license-file
Dynamic: provides
